potc/__init__.py
potc/config/__init__.py
potc/config/meta.py
potc/entry/__init__.py
potc/entry/cli/__init__.py
potc/entry/cli/base.py
potc/entry/cli/dispatch.py
potc/entry/cli/export.py
potc/entry/cli/trans.py
potc/entry/cli/utils.py
potc/fixture/__init__.py
potc/fixture/addons.py
potc/fixture/chain.py
potc/fixture/common.py
potc/fixture/imports.py
potc/rules/__init__.py
potc/rules/default.py
potc/rules/installed.py
potc/rules/system.py
potc/rules/native/__init__.py
potc/rules/native/builtin.py
potc/supports/__init__.py
potc/supports/bin.py
potc/supports/func.py
potc/testing/__init__.py
potc/testing/plugin.py
potc/testing/property.py
potc/testing/trans.py
potc/translate/__init__.py
potc/translate/base.py
potc/translate/quick.py
potc/translate/trans.py
potc-0.1.3.dist-info/LICENSE
potc-0.1.3.dist-info/METADATA
potc-0.1.3.dist-info/WHEEL
potc-0.1.3.dist-info/entry_points.txt
potc-0.1.3.dist-info/top_level.txt
potc-0.1.3.dist-info/RECORD
